zope.app.localpermission-5.0-py3.9-nspkg.pth
zope/app/localpermission/__init__.py
zope/app/localpermission/browser.zcml
zope/app/localpermission/configure.zcml
zope/app/localpermission/permission.py
zope/app/localpermission/tests.py
zope.app.localpermission-5.0.dist-info/LICENSE.txt
zope.app.localpermission-5.0.dist-info/METADATA
zope.app.localpermission-5.0.dist-info/WHEEL
zope.app.localpermission-5.0.dist-info/namespace_packages.txt
zope.app.localpermission-5.0.dist-info/top_level.txt
zope.app.localpermission-5.0.dist-info/RECORD
