Metadata-Version: 2.1
Name: zope.app.localpermission
Version: 5.0
Summary: Local Persistent Permissions for zope.security
Home-page: https://github.com/zopefoundation/zope.app.localpermission
Author: Zope Corporation and Contributors
Author-email: zope-dev@zope.dev
License: ZPL 2.1
Keywords: zope security persistent local permission
Classifier: Development Status :: 5 - Production/Stable
Classifier: Environment :: Web Environment
Classifier: Intended Audience :: Developers
Classifier: License :: OSI Approved :: Zope Public License
Classifier: Programming Language :: Python
Classifier: Programming Language :: Python :: 3
Classifier: Programming Language :: Python :: 3.7
Classifier: Programming Language :: Python :: 3.8
Classifier: Programming Language :: Python :: 3.9
Classifier: Programming Language :: Python :: 3.10
Classifier: Programming Language :: Python :: 3.11
Classifier: Programming Language :: Python :: Implementation :: CPython
Classifier: Programming Language :: Python :: Implementation :: PyPy
Classifier: Natural Language :: English
Classifier: Operating System :: OS Independent
Classifier: Topic :: Internet :: WWW/HTTP
Classifier: Framework :: Zope :: 3
Requires-Python: >=3.7
License-File: LICENSE.txt
Requires-Dist: setuptools
Requires-Dist: persistent
Requires-Dist: zope.component
Requires-Dist: zope.i18nmessageid
Requires-Dist: zope.interface
Requires-Dist: zope.location
Requires-Dist: zope.security
Provides-Extra: test
Requires-Dist: zope.annotation ; extra == 'test'
Requires-Dist: zope.configuration ; extra == 'test'
Requires-Dist: zope.testing ; extra == 'test'
Requires-Dist: zope.testrunner ; extra == 'test'
